odoo/addons/picking_product_warn_message/README.rst
odoo/addons/picking_product_warn_message/__init__.py
odoo/addons/picking_product_warn_message/__manifest__.py
odoo/addons/picking_product_warn_message/i18n/es.po
odoo/addons/picking_product_warn_message/models/__init__.py
odoo/addons/picking_product_warn_message/models/product.py
odoo/addons/picking_product_warn_message/models/stock_picking.py
odoo/addons/picking_product_warn_message/readme/CONFIGURE.md
odoo/addons/picking_product_warn_message/readme/CONTRIBUTORS.md
odoo/addons/picking_product_warn_message/readme/DESCRIPTION.md
odoo/addons/picking_product_warn_message/readme/USAGE.md
odoo/addons/picking_product_warn_message/static/description/icon.png
odoo/addons/picking_product_warn_message/static/description/index.html
odoo/addons/picking_product_warn_message/views/product_views.xml
odoo/addons/picking_product_warn_message/views/stock_picking_views.xml
odoo_addon_picking_product_warn_message-17.0.1.0.0.1.dist-info/METADATA
odoo_addon_picking_product_warn_message-17.0.1.0.0.1.dist-info/WHEEL
odoo_addon_picking_product_warn_message-17.0.1.0.0.1.dist-info/top_level.txt
odoo_addon_picking_product_warn_message-17.0.1.0.0.1.dist-info/RECORD
